{
  "tab_list": [
    {
      "msg1": "众邦理财30天",
      "msg2": "4.0%",
      "msg3": "众邦理财30天",
      "type": "活期"
    },
    {
      "msg1": "众邦理财30天",
      "msg2": "4.0%",
      "msg3": "众邦理财30天",
      "type": "活期"
    },
    {
      "msg1": "众邦理财30天",
      "msg2": "4.0%",
      "msg3": "众邦理财30天",
      "type": "活期"
    },
    {
      "msg1": "众邦理财30天",
      "msg2": "4.0%",
      "msg3": "众邦理财30天",
      "type": "活期"
    },
    {
      "msg1": "众邦理财30天",
      "msg2": "4.0%",
      "msg3": "众邦理财30天",
      "type": "活期"
    },
    {
      "msg1": "众邦理财30天",
      "msg2": "4.0%",
      "msg3": "众邦理财30天",
      "type": "活期"
    },
    {
      "msg1": "众邦理财30天",
      "msg2": "4.0%",
      "msg3": "众邦理财30天",
      "type": "活期"
    },
    {
      "msg1": "众邦理财30天",
      "msg2": "4.0%",
      "msg3": "众邦理财30天",
      "type": "活期"
    },
    {
      "msg1": "众邦理财30天",
      "msg2": "4.0%",
      "msg3": "众邦理财30天",
      "type": "活期"
    },
    {
      "msg1": "众邦理财30天",
      "msg2": "4.0%",
      "msg3": "众邦理财30天",
      "type": "活期"
    }
  ]
}